{
  "name": "@rightcapital/eslint-config-base",
  "entries": [
    {
      "date": "Thu, 11 Apr 2024 02:47:15 GMT",
      "version": "22.0.0",
      "tag": "@rightcapital/eslint-config-base_v22.0.0",
      "comments": {
        "major": [
          {
            "author": "29139614+renovate[bot]@users.noreply.github.com",
            "package": "@rightcapital/eslint-config-base",
            "commit": "8ff6fc6687adeb5f019e3f9629d53e1003c693f3",
            "comment": "fix(deps): update eslint rule and plugin updates"
          }
        ]
      }
    },
    {
      "date": "Thu, 28 Mar 2024 02:58:31 GMT",
      "version": "21.0.0",
      "tag": "@rightcapital/eslint-config-base_v21.0.0",
      "comments": {
        "major": [
          {
            "author": "29139614+renovate[bot]@users.noreply.github.com",
            "package": "@rightcapital/eslint-config-base",
            "commit": "0fe6434febcf35f0f905879ff3e5b5af46013174",
            "comment": "fix(deps): update eslint rule and plugin updates"
          }
        ]
      }
    },
    {
      "date": "Tue, 19 Mar 2024 01:43:17 GMT",
      "version": "20.1.1",
      "tag": "@rightcapital/eslint-config-base_v20.1.1",
      "comments": {
        "patch": [
          {
            "author": "29139614+renovate[bot]@users.noreply.github.com",
            "package": "@rightcapital/eslint-config-base",
            "commit": "b0454355fb6d49ab507b77501289a0f8867ccc5c",
            "comment": "fix(deps): update dependencies (non-major)"
          }
        ]
      }
    },
    {
      "date": "Mon, 26 Feb 2024 05:50:35 GMT",
      "version": "19.0.2",
      "tag": "@rightcapital/eslint-config-base_v19.0.2",
      "comments": {
        "patch": [
          {
            "author": "29139614+renovate[bot]@users.noreply.github.com",
            "package": "@rightcapital/eslint-config-base",
            "commit": "7f2eb998e7505e47cf29b3991f3f300f5210e073",
            "comment": "fix(deps): update dependencies (non-major)"
          }
        ]
      }
    },
    {
      "date": "Sun, 18 Feb 2024 02:27:41 GMT",
      "version": "19.0.1",
      "tag": "@rightcapital/eslint-config-base_v19.0.1",
      "comments": {
        "patch": [
          {
            "author": "29139614+renovate[bot]@users.noreply.github.com",
            "package": "@rightcapital/eslint-config-base",
            "commit": "4f884d7680310d30c632edc3b23d310d11eca727",
            "comment": "fix(deps): update dependencies (non-major)"
          }
        ]
      }
    },
    {
      "date": "Tue, 30 Jan 2024 05:55:09 GMT",
      "version": "19.0.0",
      "tag": "@rightcapital/eslint-config-base_v19.0.0",
      "comments": {
        "major": [
          {
            "author": "29139614+renovate[bot]@users.noreply.github.com",
            "package": "@rightcapital/eslint-config-base",
            "commit": "95f1ca3e267cedd89ae3ca1768915d3c6845a097",
            "comment": "fix(deps): update eslint rule and plugin updates"
          }
        ]
      }
    },
    {
      "date": "Tue, 30 Jan 2024 03:43:18 GMT",
      "version": "18.0.1",
      "tag": "@rightcapital/eslint-config-base_v18.0.1",
      "comments": {
        "patch": [
          {
            "author": "29139614+renovate[bot]@users.noreply.github.com",
            "package": "@rightcapital/eslint-config-base",
            "commit": "daddd15726b607accef5acf1f85dd25dca2052cf",
            "comment": "fix(deps): update dependencies (non-major)"
          }
        ]
      }
    },
    {
      "date": "Tue, 23 Jan 2024 03:19:49 GMT",
      "version": "18.0.0",
      "tag": "@rightcapital/eslint-config-base_v18.0.0",
      "comments": {
        "major": [
          {
            "author": "29139614+renovate[bot]@users.noreply.github.com",
            "package": "@rightcapital/eslint-config-base",
            "commit": "2c4ac68dccbe16de69daee9f72d89d6bc949fb69",
            "comment": "fix(deps): update eslint rule and plugin updates"
          }
        ]
      }
    },
    {
      "date": "Tue, 23 Jan 2024 02:25:14 GMT",
      "version": "17.0.3",
      "tag": "@rightcapital/eslint-config-base_v17.0.3",
      "comments": {
        "patch": [
          {
            "author": "29139614+renovate[bot]@users.noreply.github.com",
            "package": "@rightcapital/eslint-config-base",
            "commit": "918c6275bd8b2aac8e12440fccaa74daa58454ee",
            "comment": "chore(deps): update pnpm to v8.14.2"
          }
        ]
      }
    },
    {
      "date": "Thu, 11 Jan 2024 03:12:31 GMT",
      "version": "17.0.2",
      "tag": "@rightcapital/eslint-config-base_v17.0.2",
      "comments": {
        "patch": [
          {
            "author": "29139614+renovate[bot]@users.noreply.github.com",
            "package": "@rightcapital/eslint-config-base",
            "commit": "7dd171365c45443dbdd6b8830bf0b774d93c9e08",
            "comment": "fix(deps): update dependencies (non-major)"
          }
        ]
      }
    },
    {
      "date": "Thu, 04 Jan 2024 05:17:02 GMT",
      "version": "17.0.1",
      "tag": "@rightcapital/eslint-config-base_v17.0.1",
      "comments": {
        "patch": [
          {
            "author": "29139614+renovate[bot]@users.noreply.github.com",
            "package": "@rightcapital/eslint-config-base",
            "commit": "a09288138aa0609be88429db61a44a6db4acedd9",
            "comment": "fix(deps): update dependencies (non-major)"
          }
        ]
      }
    },
    {
      "date": "Mon, 27 Nov 2023 07:31:40 GMT",
      "version": "16.0.1",
      "tag": "@rightcapital/eslint-config-base_v16.0.1",
      "comments": {
        "patch": [
          {
            "author": "29139614+renovate[bot]@users.noreply.github.com",
            "package": "@rightcapital/eslint-config-base",
            "commit": "baeddd11a777e965e728f9a87257938b078ee4e5",
            "comment": "fix(deps): update dependencies (non-major)"
          }
        ]
      }
    },
    {
      "date": "Thu, 23 Nov 2023 03:10:37 GMT",
      "version": "16.0.0",
      "tag": "@rightcapital/eslint-config-base_v16.0.0",
      "comments": {
        "major": [
          {
            "author": "29139614+renovate[bot]@users.noreply.github.com",
            "package": "@rightcapital/eslint-config-base",
            "commit": "b14394447f7056cf9d1839559e0e88c1ddbced64",
            "comment": "fix(deps): update eslint rule and plugin updates"
          }
        ]
      }
    },
    {
      "date": "Tue, 21 Nov 2023 02:52:14 GMT",
      "version": "15.0.1",
      "tag": "@rightcapital/eslint-config-base_v15.0.1",
      "comments": {
        "patch": [
          {
            "author": "29139614+renovate[bot]@users.noreply.github.com",
            "package": "@rightcapital/eslint-config-base",
            "commit": "5690b6fbe666a7cbc327fc4e08c04913521edc0b",
            "comment": "fix(deps): update dependencies (non-major)"
          }
        ]
      }
    },
    {
      "date": "Tue, 14 Nov 2023 06:12:57 GMT",
      "version": "14.0.2",
      "tag": "@rightcapital/eslint-config-base_v14.0.2",
      "comments": {
        "patch": [
          {
            "author": "29139614+renovate[bot]@users.noreply.github.com",
            "package": "@rightcapital/eslint-config-base",
            "commit": "1851128a77cda9a2aa6acf71daa2c69b59d15c0f",
            "comment": "chore(deps): update pnpm to v8.10.4"
          }
        ]
      }
    },
    {
      "date": "Mon, 13 Nov 2023 07:57:22 GMT",
      "version": "14.0.1",
      "tag": "@rightcapital/eslint-config-base_v14.0.1",
      "comments": {
        "patch": [
          {
            "author": "29139614+renovate[bot]@users.noreply.github.com",
            "package": "@rightcapital/eslint-config-base",
            "commit": "e9ed3c325409336a04423b8aa46b6b9151d5f955",
            "comment": "fix(deps): update dependencies (non-major)"
          }
        ]
      }
    },
    {
      "date": "Mon, 06 Nov 2023 02:25:57 GMT",
      "version": "13.0.0",
      "tag": "@rightcapital/eslint-config-base_v13.0.0",
      "comments": {
        "none": [
          {
            "author": "29139614+renovate[bot]@users.noreply.github.com",
            "package": "@rightcapital/eslint-config-base",
            "commit": "3d7fbc96249c18cd76fabc8806265290eb52cd43",
            "comment": "chore(deps): lock file maintenance non-major updates"
          }
        ]
      }
    },
    {
      "date": "Mon, 30 Oct 2023 08:52:41 GMT",
      "version": "9.0.0",
      "tag": "@rightcapital/eslint-config-base_v9.0.0",
      "comments": {
        "major": [
          {
            "author": "29139614+renovate[bot]@users.noreply.github.com",
            "package": "@rightcapital/eslint-config-base",
            "commit": "e390c45f6c7e29e4248158e7ca71896db4a392e7",
            "comment": "fix(deps): update dependency eslint-plugin-import to v2.29.0"
          }
        ]
      }
    },
    {
      "date": "Mon, 30 Oct 2023 03:47:33 GMT",
      "version": "8.0.0",
      "tag": "@rightcapital/eslint-config-base_v8.0.0",
      "comments": {
        "none": [
          {
            "author": "29139614+renovate[bot]@users.noreply.github.com",
            "package": "@rightcapital/eslint-config-base",
            "commit": "bc5247d1d7f80111f99417a5ea01219664fa254b",
            "comment": "chore(deps): lock file maintenance non-major updates"
          }
        ]
      }
    },
    {
      "date": "Fri, 27 Oct 2023 03:04:45 GMT",
      "version": "8.0.0",
      "tag": "@rightcapital/eslint-config-base_v8.0.0",
      "comments": {
        "major": [
          {
            "author": "29139614+renovate[bot]@users.noreply.github.com",
            "package": "@rightcapital/eslint-config-base",
            "commit": "24c39914f51fd4fbee837bbf66c479a57b803283",
            "comment": "fix(deps): update eslint rule and plugin updates"
          }
        ]
      }
    },
    {
      "date": "Fri, 27 Oct 2023 01:43:09 GMT",
      "version": "7.0.2",
      "tag": "@rightcapital/eslint-config-base_v7.0.2",
      "comments": {
        "patch": [
          {
            "author": "29139614+renovate[bot]@users.noreply.github.com",
            "package": "@rightcapital/eslint-config-base",
            "commit": "b6ead8470ba7225dd8bb4b797c3b562758655952",
            "comment": "chore(deps): update pnpm to v8.9.2"
          }
        ]
      }
    },
    {
      "date": "Thu, 26 Oct 2023 08:49:17 GMT",
      "version": "7.0.1",
      "tag": "@rightcapital/eslint-config-base_v7.0.1",
      "comments": {
        "patch": [
          {
            "author": "29139614+renovate[bot]@users.noreply.github.com",
            "package": "@rightcapital/eslint-config-base",
            "commit": "86a6d34dfbe421661b58a276da3a4180a481e02f",
            "comment": "chore(deps): update pnpm to v8.8.0"
          }
        ]
      }
    },
    {
      "date": "Tue, 26 Sep 2023 08:20:39 GMT",
      "version": "7.0.0",
      "tag": "@rightcapital/eslint-config-base_v7.0.0",
      "comments": {
        "major": [
          {
            "author": "29139614+renovate[bot]@users.noreply.github.com",
            "package": "@rightcapital/eslint-config-base",
            "commit": "5c3d790fb7719d5e4653f8cfff216ff15b14dd3b",
            "comment": "fix(deps): update eslint rule and plugin updates"
          }
        ]
      }
    },
    {
      "date": "Tue, 26 Sep 2023 08:16:27 GMT",
      "version": "6.0.3",
      "tag": "@rightcapital/eslint-config-base_v6.0.3",
      "comments": {
        "patch": [
          {
            "author": "29139614+renovate[bot]@users.noreply.github.com",
            "package": "@rightcapital/eslint-config-base",
            "commit": "6ec2c186b2262054c6a5ba8777ce8588baa3d5cd",
            "comment": "chore(deps): update dependencies (non-major)"
          }
        ]
      }
    },
    {
      "date": "Tue, 26 Sep 2023 07:35:05 GMT",
      "version": "6.0.2",
      "tag": "@rightcapital/eslint-config-base_v6.0.2",
      "comments": {
        "patch": [
          {
            "author": "i@frantic1048.com",
            "package": "@rightcapital/eslint-config-base",
            "commit": "6bf4d0e9b71f6f6ed8df70deffcaf2b874d22acf",
            "comment": "feat: use eslint-plugin-i to replace eslint-plugin-import for faster linting"
          }
        ]
      }
    },
    {
      "date": "Fri, 15 Sep 2023 08:53:02 GMT",
      "version": "6.0.1",
      "tag": "@rightcapital/eslint-config-base_v6.0.1",
      "comments": {
        "patch": [
          {
            "author": "email not defined",
            "package": "@rightcapital/eslint-config-base",
            "commit": "9848a685b74f4386e815fcd6fb69cf498dbf2cfb",
            "comment": "fix(deps): update dependencies (non-major)"
          }
        ]
      }
    }
  ]
}
